setup.py
simplestopwatch/__init__.py
simplestopwatch.egg-info/PKG-INFO
simplestopwatch.egg-info/SOURCES.txt
simplestopwatch.egg-info/dependency_links.txt
simplestopwatch.egg-info/top_level.txt
simplestopwatch.egg-info/zip-safe