Metadata-Version: 1.1
Name: simplestopwatch
Version: 0.3.3
Summary: A very simple python module for measuring elapsed time.
Home-page: https://github.com/kamakazikamikaze/simplestopwatch
Author: John Paulett <http://blog.7oars.com>, Kent Coble <https://github.com/kamakazikamikaze
Author-email: john -at- 7oars.com, coblekent@gmail.com
License: BSD
Download-URL: https://github.com/kamakazikamikaze/simplestopwatch
Keywords: timer,stopwatch,execution,timeit
Platform: POSIX
Platform: Windows
Classifier: License :: OSI Approved :: BSD License
Classifier: Operating System :: OS Independent
Classifier: Programming Language :: Python
Classifier: Topic :: Software Development :: Libraries :: Python Modules
Classifier: Development Status :: 4 - Beta
Classifier: Intended Audience :: Developers
